AdvancedHTMLParser-6.1.0.data/scripts/formatHTML
AdvancedHTMLParser/exceptions.py
AdvancedHTMLParser/Formatter.py
AdvancedHTMLParser/SpecialAttributes.py
AdvancedHTMLParser/constants.py
AdvancedHTMLParser/Tags.py
AdvancedHTMLParser/Parser.py
AdvancedHTMLParser/__init__.py
AdvancedHTMLParser-6.1.0.dist-info/metadata.json
AdvancedHTMLParser-6.1.0.dist-info/WHEEL
AdvancedHTMLParser-6.1.0.dist-info/RECORD
AdvancedHTMLParser-6.1.0.dist-info/DESCRIPTION.rst
AdvancedHTMLParser-6.1.0.dist-info/top_level.txt
AdvancedHTMLParser-6.1.0.dist-info/METADATA
