Metadata-Version: 2.0
Name: AdvancedHTMLParser
Version: 6.1.0
Summary: A Powerful HTML Parser/Scraper/Validator that constructs a modifiable, searchable DOM tree, and includes many standard JS DOM functions (getElementsBy*, appendChild, etc) and additional methods
Home-page: https://github.com/kata198/AdvancedHTMLParser
Author: Tim Savannah
Author-email: kata198@gmail.com
License: LGPLv3
Keywords: html,parser,tree,DOM,getElementsByName,getElementById,getElementsByClassName,simple,python,xml,HTMLParser,getElementsByTagName,getElementsByAttr,javascript,parse,scrape,test,SimpleHTMLParser,modify,JS,write
Platform: UNKNOWN
Classifier: Development Status :: 5 - Production/Stable
Classifier: Programming Language :: Python
Classifier: License :: OSI Approved :: GNU Lesser General Public License v3 (LGPLv3)
Classifier: Programming Language :: Python :: 2
Classifier: Programming Language :: Python :: 2
Classifier: Programming Language :: Python :: 2.6
Classifier: Programming Language :: Python :: 2.7
Classifier: Programming Language :: Python :: 3
Classifier: Programming Language :: Python :: 3.3
Classifier: Programming Language :: Python :: 3.4
Classifier: Topic :: Internet :: WWW/HTTP
Classifier: Topic :: Text Processing :: Markup :: HTML
Classifier: Topic :: Software Development :: Libraries :: Python Modules
